{
  "generated_at": "2026-03-13T14:33:34.369625",
  "run_id": "1c76f483",
  "total_pages_scanned": 1,
  "total_signals_found": 1,
  "top_entries": [
    {
      "signal": {
        "signal_id": "91181f504d2b03ea",
        "company_name": "AppOmni",
        "company_type": "competitor",
        "source_url": "https://appomni.com/blog/new-aws-partnership",
        "signal_type": "competitor_move",
        "title": "AppOmni expands AWS co-sell agreement",
        "summary": "AppOmni announced an expanded co-sell agreement with AWS targeting enterprise SaaS security buyers. The deal includes joint field events and a presence in AWS Marketplace.",
        "why_it_matters": "This strengthens AppOmni's distribution into AWS-centric enterprise accounts \u2014 our primary ICP. It reduces Obsidian's window for displacing AppOmni in cloud-first deals.",
        "detected_at": "2026-03-13T14:33:34.369910",
        "publish_date": null,
        "related_partner": "AWS",
        "affected_segment": "Enterprise Cloud / AWS-native accounts",
        "confidence": 0.92,
        "priority": "high",
        "priority_score": 0.88,
        "priority_rationale": "",
        "is_new": true
      },
      "actions": [
        {
          "signal_id": "91181f504d2b03ea",
          "action_type": "competitive_response",
          "description": "Coordinate with Optiv and GuidePoint on AWS-native account targeting. Position Obsidian's runtime identity detection as complementary to AppOmni's posture visibility.",
          "suggested_owner": "Partner Manager",
          "suggested_partners": [
            "Optiv",
            "GuidePoint Security"
          ],
          "suggested_accounts": [
            "Enterprise FSI on AWS",
            "Cloud-first SaaS companies"
          ],
          "outreach_draft": "Hey [Partner] \u2014 AppOmni just deepened their AWS co-sell. Want to jump on a quick call to align on how we position Obsidian in your AWS-focused accounts? Happy to bring the AE team."
        }
      ]
    }
  ],
  "summary_narrative": "Ecosystem Radar scanned 1 pages and surfaced 1 new signals, with 1 prioritized for action. 1 high-priority signal(s) from AppOmni require near-term partner response. Recommended actions are included below with suggested owners and outreach drafts.",
  "watchlist_coverage": {
    "competitor": 15,
    "partner": 14
  }
}